{
  "__inputs": [
    {
      "name": "DS_CLOUD-SP-DEV-LAB-METRICS",
      "label": "cloud-sp-dev-lab-metrics",
      "description": "",
      "type": "datasource",
      "pluginId": "prometheus",
      "pluginName": "Prometheus"
    },
    {
      "name": "DS_EXPRESSION",
      "label": "Expression",
      "description": "",
      "type": "datasource",
      "pluginId": "__expr__"
    }
  ],
  "__elements": {},
  "__requires": [
    {
      "type": "datasource",
      "id": "__expr__",
      "version": "1.0.0"
    },
    {
      "type": "grafana",
      "id": "grafana",
      "name": "Grafana",
      "version": "9.0.6"
    },
    {
      "type": "panel",
      "id": "graph",
      "name": "Graph (old)",
      "version": ""
    },
    {
      "type": "datasource",
      "id": "prometheus",
      "name": "Prometheus",
      "version": "1.0.0"
    },
    {
      "type": "panel",
      "id": "stat",
      "name": "Stat",
      "version": ""
    },
    {
      "type": "panel",
      "id": "table",
      "name": "Table",
      "version": ""
    }
  ],
  "annotations": {
    "list": [
      {
        "builtIn": 1,
        "datasource": {
          "type": "datasource",
          "uid": "grafana"
        },
        "enable": true,
        "hide": true,
        "iconColor": "rgba(0, 211, 255, 1)",
        "name": "Annotations & Alerts",
        "target": {
          "limit": 100,
          "matchAny": false,
          "tags": [],
          "type": "dashboard"
        },
        "type": "dashboard"
      }
    ]
  },
  "description": "This is complete dashboard to monitor libvirt hypervisors and virtual machines",
  "editable": true,
  "fiscalYearStartMonth": 0,
  "gnetId": 13633,
  "graphTooltip": 1,
  "id": null,
  "links": [],
  "liveNow": false,
  "panels": [
    {
      "collapsed": false,
      "datasource": {
        "type": "prometheus",
        "uid": "Y4EtCc7Vk"
      },
      "gridPos": {
        "h": 1,
        "w": 24,
        "x": 0,
        "y": 0
      },
      "id": 91,
      "panels": [],
      "targets": [
        {
          "datasource": {
            "type": "prometheus",
            "uid": "Y4EtCc7Vk"
          },
          "refId": "A"
        }
      ],
      "title": "General",
      "type": "row"
    },
    {
      "datasource": {
        "type": "prometheus",
        "uid": "Prometheus"
      },
      "fieldConfig": {
        "defaults": {
          "color": {
            "mode": "thresholds"
          },
          "mappings": [],
          "thresholds": {
            "mode": "absolute",
            "steps": [
              {
                "color": "green",
                "value": null
              },
              {
                "color": "red",
                "value": 80
              }
            ]
          }
        },
        "overrides": []
      },
      "gridPos": {
        "h": 3,
        "w": 5,
        "x": 0,
        "y": 1
      },
      "id": 126,
      "options": {
        "colorMode": "value",
        "graphMode": "area",
        "justifyMode": "auto",
        "orientation": "auto",
        "reduceOptions": {
          "calcs": [
            "lastNotNull"
          ],
          "fields": "",
          "values": false
        },
        "textMode": "auto"
      },
      "pluginVersion": "9.0.6",
      "targets": [
        {
          "datasource": {
            "type": "prometheus",
            "uid": "Prometheus"
          },
          "editorMode": "code",
          "exemplar": false,
          "expr": "sum(openstack_nova_total_vms{})-count(libvirt_domain_memory_stats_used_percent==0)",
          "format": "table",
          "instant": true,
          "legendFormat": "{{ instance }} --Hostname",
          "range": false,
          "refId": "A"
        }
      ],
      "title": "Count VM  in Active+Pause+Error",
      "type": "stat"
    },
    {
      "datasource": {
        "type": "prometheus",
        "uid": "Prometheus"
      },
      "fieldConfig": {
        "defaults": {
          "color": {
            "mode": "thresholds"
          },
          "mappings": [
            {
              "id": 0,
              "op": "=",
              "text": "N/A",
              "type": 1,
              "value": "null"
            }
          ],
          "thresholds": {
            "mode": "absolute",
            "steps": [
              {
                "color": "green",
                "value": null
              },
              {
                "color": "red",
                "value": 2000
              }
            ]
          },
          "unit": "none"
        },
        "overrides": []
      },
      "gridPos": {
        "h": 3,
        "w": 4,
        "x": 5,
        "y": 1
      },
      "id": 129,
      "links": [],
      "maxDataPoints": 100,
      "options": {
        "colorMode": "value",
        "graphMode": "area",
        "justifyMode": "auto",
        "orientation": "horizontal",
        "reduceOptions": {
          "calcs": [
            "lastNotNull"
          ],
          "fields": "",
          "values": false
        },
        "textMode": "auto"
      },
      "pluginVersion": "9.0.6",
      "targets": [
        {
          "datasource": {
            "type": "prometheus",
            "uid": "Prometheus"
          },
          "editorMode": "code",
          "exemplar": false,
          "expr": "sum(openstack_nova_total_vms)",
          "format": "time_series",
          "hide": true,
          "instant": true,
          "intervalFactor": 1,
          "range": false,
          "refId": "A"
        },
        {
          "datasource": {
            "type": "prometheus",
            "uid": "Prometheus"
          },
          "editorMode": "code",
          "exemplar": false,
          "expr": "sum(openstack_nova_running_vms)",
          "hide": true,
          "instant": true,
          "range": false,
          "refId": "B"
        },
        {
          "datasource": {
            "type": "__expr__",
            "uid": "${DS_EXPRESSION}"
          },
          "expression": "$A-$B",
          "hide": false,
          "refId": "Total Number of VM in Error State",
          "type": "math"
        }
      ],
      "title": "VM in Error State",
      "type": "stat"
    },
    {
      "datasource": {
        "type": "prometheus",
        "uid": "Prometheus"
      },
      "fieldConfig": {
        "defaults": {
          "color": {
            "mode": "thresholds"
          },
          "mappings": [],
          "thresholds": {
            "mode": "absolute",
            "steps": [
              {
                "color": "green",
                "value": null
              },
              {
                "color": "dark-red",
                "value": 1
              }
            ]
          }
        },
        "overrides": []
      },
      "gridPos": {
        "h": 3,
        "w": 4,
        "x": 9,
        "y": 1
      },
      "id": 127,
      "options": {
        "colorMode": "value",
        "graphMode": "area",
        "justifyMode": "auto",
        "orientation": "auto",
        "reduceOptions": {
          "calcs": [
            "lastNotNull"
          ],
          "fields": "",
          "values": false
        },
        "textMode": "auto"
      },
      "pluginVersion": "9.0.6",
      "targets": [
        {
          "datasource": {
            "type": "prometheus",
            "uid": "Prometheus"
          },
          "editorMode": "code",
          "exemplar": false,
          "expr": "count(libvirt_domain_memory_stats_used_percent==0)",
          "format": "time_series",
          "instant": false,
          "legendFormat": "{{ instance }} -- {{ instane-name }}",
          "range": true,
          "refId": "A"
        }
      ],
      "title": "Total Number of VM  in shutoff state",
      "type": "stat"
    },
    {
      "datasource": {
        "type": "prometheus",
        "uid": "Prometheus"
      },
      "description": "",
      "fieldConfig": {
        "defaults": {
          "custom": {
            "align": "auto",
            "displayMode": "auto",
            "filterable": true,
            "inspect": false
          },
          "mappings": [],
          "max": 100,
          "min": 0,
          "thresholds": {
            "mode": "absolute",
            "steps": [
              {
                "color": "green",
                "value": null
              },
              {
                "color": "#EAB839",
                "value": 80
              },
              {
                "color": "red",
                "value": 90
              }
            ]
          },
          "unit": "decbytes"
        },
        "overrides": [
          {
            "matcher": {
              "id": "byName",
              "options": "RAM Used %"
            },
            "properties": [
              {
                "id": "unit",
                "value": "percent"
              },
              {
                "id": "thresholds",
                "value": {
                  "mode": "absolute",
                  "steps": [
                    {
                      "color": "green",
                      "value": null
                    },
                    {
                      "color": "red",
                      "value": 80
                    }
                  ]
                }
              },
              {
                "id": "custom.displayMode",
                "value": "lcd-gauge"
              }
            ]
          },
          {
            "matcher": {
              "id": "byName",
              "options": "Disk Total"
            },
            "properties": [
              {
                "id": "unit",
                "value": "bytes"
              },
              {
                "id": "custom.width",
                "value": 98
              }
            ]
          },
          {
            "matcher": {
              "id": "byName",
              "options": "Host"
            },
            "properties": [
              {
                "id": "custom.width",
                "value": 141
              }
            ]
          },
          {
            "matcher": {
              "id": "byName",
              "options": "VM"
            },
            "properties": [
              {
                "id": "custom.width",
                "value": 214
              }
            ]
          },
          {
            "matcher": {
              "id": "byName",
              "options": "RAM Total"
            },
            "properties": [
              {
                "id": "custom.width",
                "value": 101
              }
            ]
          },
          {
            "matcher": {
              "id": "byName",
              "options": "RAM Used"
            },
            "properties": [
              {
                "id": "custom.width",
                "value": 98
              }
            ]
          }
        ]
      },
      "gridPos": {
        "h": 9,
        "w": 11,
        "x": 13,
        "y": 1
      },
      "id": 124,
      "options": {
        "footer": {
          "fields": "",
          "reducer": [
            "sum"
          ],
          "show": false
        },
        "frameIndex": 0,
        "showHeader": true,
        "sortBy": [
          {
            "desc": true,
            "displayName": "RAM Used %"
          }
        ]
      },
      "pluginVersion": "9.0.6",
      "targets": [
        {
          "datasource": {
            "type": "prometheus",
            "uid": "Prometheus"
          },
          "editorMode": "code",
          "expr": "libvirt_domain_memory_stats_available_bytes{instance=~\"$instance.*\"}",
          "format": "table",
          "hide": false,
          "instant": true,
          "interval": "",
          "legendFormat": "total",
          "refId": "A"
        },
        {
          "datasource": {
            "type": "prometheus",
            "uid": "Prometheus"
          },
          "editorMode": "code",
          "expr": "(libvirt_domain_memory_stats_used_percent_bytes{instance=~\"$instance.*\"} * libvirt_domain_memory_stats_available_bytes{instance=~\"$instance.*\"}) / 100",
          "format": "table",
          "hide": false,
          "instant": true,
          "interval": "",
          "legendFormat": "used",
          "refId": "B"
        },
        {
          "datasource": {
            "type": "prometheus",
            "uid": "Prometheus"
          },
          "editorMode": "code",
          "expr": "libvirt_domain_memory_stats_used_percent{instance=~\"$instance.*\"}",
          "format": "table",
          "hide": false,
          "instant": true,
          "interval": "",
          "legendFormat": "used %",
          "refId": "C"
        },
        {
          "datasource": {
            "type": "prometheus",
            "uid": "Prometheus"
          },
          "editorMode": "code",
          "expr": "libvirt_domain_block_stats_physicalsize_bytes{instance=~\"$instance.*\"}",
          "format": "table",
          "instant": true,
          "interval": "",
          "legendFormat": "Disk Size",
          "refId": "D"
        },
        {
          "datasource": {
            "type": "prometheus",
            "uid": "Prometheus"
          },
          "editorMode": "code",
          "expr": "rate(node_cpu_guest_seconds_total[5m])",
          "hide": false,
          "legendFormat": "__auto",
          "range": true,
          "refId": "E"
        }
      ],
      "title": "RAM and Disk usage on Running  vms",
      "transformations": [
        {
          "id": "filterFieldsByName",
          "options": {
            "include": {
              "names": [
                "instance",
                "Value #A",
                "Value #C",
                "Value #D",
                "instance_name",
                "domain"
              ]
            }
          }
        },
        {
          "id": "seriesToColumns",
          "options": {
            "byField": "domain"
          }
        },
        {
          "id": "organize",
          "options": {
            "excludeByName": {
              "domain": true,
              "instance 1": true,
              "instance 2": true,
              "instance 3": false,
              "instance 4": true,
              "instance_name 1": false,
              "instance_name 2": true,
              "instance_name 3": true
            },
            "indexByName": {
              "Value #A": 5,
              "Value #C": 6,
              "Value #D": 4,
              "domain": 3,
              "instance 1": 7,
              "instance 2": 8,
              "instance 3": 1,
              "instance_name 1": 2,
              "instance_name 2": 9,
              "instance_name 3": 0
            },
            "renameByName": {
              "Value #A": "RAM Total",
              "Value #B": "RAM Used",
              "Value #C": "RAM Used %",
              "Value #D": "Disk Total",
              "domain": "VM",
              "instance 3": "Host",
              "job 1": ""
            }
          }
        },
        {
          "id": "filterByValue",
          "options": {
            "filters": [
              {
                "config": {
                  "id": "greater",
                  "options": {
                    "value": 0
                  }
                },
                "fieldName": "RAM Used %"
              }
            ],
            "match": "any",
            "type": "include"
          }
        }
      ],
      "type": "table"
    },
    {
      "datasource": {
        "type": "prometheus",
        "uid": "Prometheus"
      },
      "description": "",
      "fieldConfig": {
        "defaults": {
          "custom": {
            "align": "auto",
            "displayMode": "auto",
            "filterable": true,
            "inspect": false
          },
          "mappings": [],
          "max": 100,
          "min": 0,
          "thresholds": {
            "mode": "absolute",
            "steps": [
              {
                "color": "green",
                "value": null
              },
              {
                "color": "#EAB839",
                "value": 80
              },
              {
                "color": "red",
                "value": 90
              }
            ]
          },
          "unit": "decbytes"
        },
        "overrides": [
          {
            "matcher": {
              "id": "byName",
              "options": "RAM Used %"
            },
            "properties": [
              {
                "id": "unit",
                "value": "percent"
              },
              {
                "id": "thresholds",
                "value": {
                  "mode": "absolute",
                  "steps": [
                    {
                      "color": "green",
                      "value": null
                    },
                    {
                      "color": "red",
                      "value": 80
                    }
                  ]
                }
              },
              {
                "id": "custom.displayMode",
                "value": "lcd-gauge"
              }
            ]
          },
          {
            "matcher": {
              "id": "byName",
              "options": "Disk Total"
            },
            "properties": [
              {
                "id": "unit",
                "value": "bytes"
              },
              {
                "id": "custom.width",
                "value": 98
              }
            ]
          },
          {
            "matcher": {
              "id": "byName",
              "options": "Host"
            },
            "properties": [
              {
                "id": "custom.width",
                "value": 141
              }
            ]
          },
          {
            "matcher": {
              "id": "byName",
              "options": "VM"
            },
            "properties": [
              {
                "id": "custom.width",
                "value": 214
              }
            ]
          },
          {
            "matcher": {
              "id": "byName",
              "options": "RAM Total"
            },
            "properties": [
              {
                "id": "custom.width",
                "value": 101
              }
            ]
          },
          {
            "matcher": {
              "id": "byName",
              "options": "RAM Used"
            },
            "properties": [
              {
                "id": "custom.width",
                "value": 98
              }
            ]
          }
        ]
      },
      "gridPos": {
        "h": 6,
        "w": 13,
        "x": 0,
        "y": 4
      },
      "id": 95,
      "options": {
        "footer": {
          "fields": "",
          "reducer": [
            "sum"
          ],
          "show": false
        },
        "frameIndex": 0,
        "showHeader": true,
        "sortBy": [
          {
            "desc": false,
            "displayName": "RAM Total"
          }
        ]
      },
      "pluginVersion": "9.0.6",
      "targets": [
        {
          "datasource": {
            "type": "prometheus",
            "uid": "Prometheus"
          },
          "editorMode": "code",
          "expr": "libvirt_domain_memory_stats_available_bytes{instance=~\"$instance.*\"}",
          "format": "table",
          "hide": false,
          "instant": true,
          "interval": "",
          "legendFormat": "total",
          "refId": "A"
        },
        {
          "datasource": {
            "type": "prometheus",
            "uid": "Prometheus"
          },
          "editorMode": "code",
          "expr": "(libvirt_domain_memory_stats_used_percent_bytes{instance=~\"$instance.*\"} * libvirt_domain_memory_stats_available_bytes{instance=~\"$instance.*\"}) / 100",
          "format": "table",
          "hide": false,
          "instant": true,
          "interval": "",
          "legendFormat": "used",
          "refId": "B"
        },
        {
          "datasource": {
            "type": "prometheus",
            "uid": "Prometheus"
          },
          "editorMode": "code",
          "exemplar": false,
          "expr": "libvirt_domain_memory_stats_used_percent{instance=~\"$instance.*\"}",
          "format": "table",
          "hide": false,
          "instant": true,
          "interval": "",
          "legendFormat": "used %",
          "range": false,
          "refId": "C"
        },
        {
          "datasource": {
            "type": "prometheus",
            "uid": "Prometheus"
          },
          "editorMode": "code",
          "expr": "libvirt_domain_block_stats_physicalsize_bytes{instance=~\"$instance.*\"}",
          "format": "table",
          "instant": true,
          "interval": "",
          "legendFormat": "Disk Size",
          "refId": "D"
        }
      ],
      "title": "Details of VM in shutoff state",
      "transformations": [
        {
          "id": "filterFieldsByName",
          "options": {
            "include": {
              "names": [
                "domain",
                "instance",
                "instance_name",
                "Value #A",
                "Value #C",
                "Value #D",
                "project_name"
              ]
            }
          }
        },
        {
          "id": "seriesToColumns",
          "options": {
            "byField": "domain"
          }
        },
        {
          "id": "organize",
          "options": {
            "excludeByName": {
              "Value #A": true,
              "Value #C": false,
              "Value #D": true,
              "domain": false,
              "instance 1": true,
              "instance 2": false,
              "instance 3": true,
              "instance 4": true,
              "instance_name 1": false,
              "instance_name 2": true,
              "instance_name 3": true,
              "project_name 2": true,
              "project_name 3": true
            },
            "indexByName": {
              "Value #A": 4,
              "Value #C": 12,
              "Value #D": 3,
              "domain": 2,
              "instance 1": 5,
              "instance 2": 6,
              "instance 3": 1,
              "instance_name 1": 0,
              "instance_name 2": 7,
              "instance_name 3": 8,
              "project_name 1": 9,
              "project_name 2": 10,
              "project_name 3": 11
            },
            "renameByName": {
              "Value #A": "RAM Total",
              "Value #B": "RAM Used",
              "Value #C": "RAM Used %",
              "Value #D": "Disk Total",
              "domain": "VM Name on hypervisor",
              "instance 1": "",
              "instance 2": "Host",
              "instance 3": "Host",
              "instance_name 1": "instance_name",
              "job 1": ""
            }
          }
        },
        {
          "id": "filterByValue",
          "options": {
            "filters": [
              {
                "config": {
                  "id": "equal",
                  "options": {
                    "value": 0
                  }
                },
                "fieldName": "RAM Used %"
              }
            ],
            "match": "any",
            "type": "include"
          }
        }
      ],
      "type": "table"
    },
    {
      "aliasColors": {
        "Busy": "#EAB839",
        "Busy Iowait": "#890F02",
        "Busy other": "#1F78C1",
        "Idle": "#052B51",
        "Idle - Waiting for something to happen": "#052B51",
        "guest": "#9AC48A",
        "idle": "#052B51",
        "iowait": "#EAB839",
        "irq": "#BF1B00",
        "nice": "#C15C17",
        "softirq": "#E24D42",
        "steal": "#FCE2DE",
        "system": "#508642",
        "user": "#5195CE"
      },
      "bars": false,
      "dashLength": 10,
      "dashes": false,
      "datasource": {
        "type": "prometheus",
        "uid": "Prometheus"
      },
      "decimals": 2,
      "description": "Basic CPU info",
      "fieldConfig": {
        "defaults": {
          "links": []
        },
        "overrides": []
      },
      "fill": 4,
      "fillGradient": 0,
      "gridPos": {
        "h": 7,
        "w": 12,
        "x": 0,
        "y": 10
      },
      "hiddenSeries": false,
      "id": 99,
      "legend": {
        "alignAsTable": false,
        "avg": false,
        "current": false,
        "max": false,
        "min": false,
        "rightSide": false,
        "show": true,
        "sideWidth": 250,
        "total": false,
        "values": false
      },
      "lines": true,
      "linewidth": 1,
      "links": [],
      "maxPerRow": 6,
      "nullPointMode": "null",
      "options": {
        "alertThreshold": true
      },
      "percentage": true,
      "pluginVersion": "9.0.6",
      "pointradius": 5,
      "points": false,
      "renderer": "flot",
      "seriesOverrides": [
        {
          "$$hashKey": "object:3138",
          "alias": "Busy Iowait",
          "color": "#890F02"
        },
        {
          "$$hashKey": "object:3139",
          "alias": "Idle",
          "color": "#7EB26D"
        },
        {
          "$$hashKey": "object:3140",
          "alias": "Busy System",
          "color": "#EAB839"
        },
        {
          "$$hashKey": "object:3141",
          "alias": "Busy User",
          "color": "#0A437C"
        },
        {
          "$$hashKey": "object:3142",
          "alias": "Busy Other",
          "color": "#6D1F62"
        }
      ],
      "spaceLength": 10,
      "stack": true,
      "steppedLine": false,
      "targets": [
        {
          "datasource": {
            "type": "prometheus",
            "uid": "Prometheus"
          },
          "editorMode": "code",
          "expr": "sum by (instance)(irate(node_cpu_seconds_total{mode=\"system\",instance=~\"$instance.*\",job=\"node_exporter\"}[5m])) * 100",
          "format": "time_series",
          "hide": false,
          "interval": "",
          "intervalFactor": 2,
          "legendFormat": "Busy System",
          "range": true,
          "refId": "A",
          "step": 240
        },
        {
          "datasource": {
            "type": "prometheus",
            "uid": "Prometheus"
          },
          "editorMode": "code",
          "expr": "sum by (instance)(irate(node_cpu_seconds_total{mode='user',instance=~\"$instance.*\",job=\"node_exporter\"}[5m])) * 100",
          "format": "time_series",
          "hide": false,
          "interval": "",
          "intervalFactor": 2,
          "legendFormat": "Busy User",
          "range": true,
          "refId": "B",
          "step": 240
        },
        {
          "datasource": {
            "type": "prometheus",
            "uid": "Prometheus"
          },
          "editorMode": "code",
          "expr": "sum by (instance)(irate(node_cpu_seconds_total{mode='iowait',instance=~\"$instance.*\",job=\"node_exporter\"}[5m])) * 100",
          "format": "time_series",
          "interval": "",
          "intervalFactor": 2,
          "legendFormat": "Busy Iowait",
          "range": true,
          "refId": "C",
          "step": 240
        },
        {
          "datasource": {
            "type": "prometheus",
            "uid": "Prometheus"
          },
          "editorMode": "code",
          "expr": "sum by (instance)(irate(node_cpu_seconds_total{mode=~\".*irq\",instance=~\"$instance.*\",job=\"node_exporter\"}[5m])) * 100",
          "format": "time_series",
          "interval": "",
          "intervalFactor": 2,
          "legendFormat": "Busy IRQs",
          "range": true,
          "refId": "D",
          "step": 240
        },
        {
          "datasource": {
            "type": "prometheus",
            "uid": "Prometheus"
          },
          "editorMode": "code",
          "expr": "sum (irate(node_cpu_seconds_total{mode!='idle',mode!='user',mode!='system',mode!='iowait',mode!='irq',mode!='softirq',instance=~\"$instance.*\",job=\"node_exporter\"}[5m])) * 100",
          "format": "time_series",
          "interval": "",
          "intervalFactor": 2,
          "legendFormat": "Busy Other",
          "range": true,
          "refId": "E",
          "step": 240
        },
        {
          "datasource": {
            "type": "prometheus",
            "uid": "Prometheus"
          },
          "editorMode": "code",
          "expr": "sum by (mode)(irate(node_cpu_seconds_total{mode='idle',instance=~\"$instance.*\",job=\"node_exporter\"}[5m])) * 100",
          "format": "time_series",
          "interval": "",
          "intervalFactor": 2,
          "legendFormat": "Idle",
          "range": true,
          "refId": "F",
          "step": 240
        }
      ],
      "thresholds": [],
      "timeRegions": [],
      "title": "CPU load on physical host",
      "tooltip": {
        "shared": true,
        "sort": 0,
        "value_type": "individual"
      },
      "type": "graph",
      "xaxis": {
        "mode": "time",
        "show": true,
        "values": []
      },
      "yaxes": [
        {
          "$$hashKey": "object:3173",
          "format": "short",
          "label": "",
          "logBase": 1,
          "max": "100",
          "min": "0",
          "show": true
        },
        {
          "$$hashKey": "object:3174",
          "format": "short",
          "logBase": 1,
          "show": false
        }
      ],
      "yaxis": {
        "align": false
      }
    },
    {
      "aliasColors": {},
      "bars": false,
      "dashLength": 10,
      "dashes": false,
      "datasource": {
        "type": "prometheus",
        "uid": "Prometheus"
      },
      "fill": 1,
      "fillGradient": 0,
      "gridPos": {
        "h": 7,
        "w": 12,
        "x": 12,
        "y": 10
      },
      "hiddenSeries": false,
      "id": 89,
      "legend": {
        "avg": false,
        "current": false,
        "max": false,
        "min": false,
        "show": true,
        "total": false,
        "values": false
      },
      "lines": true,
      "linewidth": 1,
      "nullPointMode": "null",
      "options": {
        "alertThreshold": true
      },
      "percentage": false,
      "pluginVersion": "9.0.6",
      "pointradius": 2,
      "points": false,
      "renderer": "flot",
      "seriesOverrides": [],
      "spaceLength": 10,
      "stack": false,
      "steppedLine": false,
      "targets": [
        {
          "datasource": {
            "type": "prometheus",
            "uid": "Prometheus"
          },
          "editorMode": "code",
          "expr": "node_memory_MemFree_bytes{instance=~\"$instance.*\",job=\"node_exporter\"}",
          "interval": "",
          "legendFormat": "{{instance}}",
          "range": true,
          "refId": "A"
        }
      ],
      "thresholds": [],
      "timeRegions": [],
      "title": "FREE memory on physical host",
      "tooltip": {
        "shared": true,
        "sort": 0,
        "value_type": "individual"
      },
      "type": "graph",
      "xaxis": {
        "mode": "time",
        "show": true,
        "values": []
      },
      "yaxes": [
        {
          "$$hashKey": "object:84",
          "format": "bytes",
          "logBase": 1,
          "max": "550000000000",
          "show": true
        },
        {
          "$$hashKey": "object:85",
          "format": "short",
          "logBase": 1,
          "show": true
        }
      ],
      "yaxis": {
        "align": false
      }
    },
    {
      "collapsed": false,
      "datasource": {
        "type": "prometheus",
        "uid": "Y4EtCc7Vk"
      },
      "gridPos": {
        "h": 1,
        "w": 24,
        "x": 0,
        "y": 17
      },
      "id": 76,
      "panels": [],
      "targets": [
        {
          "datasource": {
            "type": "prometheus",
            "uid": "Y4EtCc7Vk"
          },
          "refId": "A"
        }
      ],
      "title": "Memory Stats ",
      "type": "row"
    },
    {
      "aliasColors": {},
      "bars": false,
      "dashLength": 10,
      "dashes": false,
      "datasource": {
        "type": "prometheus",
        "uid": "Prometheus"
      },
      "description": "The amount of memory in percent, that used by domain.",
      "fill": 0,
      "fillGradient": 0,
      "gridPos": {
        "h": 8,
        "w": 12,
        "x": 0,
        "y": 18
      },
      "hiddenSeries": false,
      "id": 79,
      "legend": {
        "avg": false,
        "current": false,
        "max": false,
        "min": false,
        "show": true,
        "total": false,
        "values": false
      },
      "lines": true,
      "linewidth": 1,
      "nullPointMode": "null",
      "options": {
        "alertThreshold": true
      },
      "percentage": false,
      "pluginVersion": "9.0.6",
      "pointradius": 2,
      "points": false,
      "renderer": "flot",
      "seriesOverrides": [],
      "spaceLength": 10,
      "stack": false,
      "steppedLine": false,
      "targets": [
        {
          "datasource": {
            "type": "prometheus",
            "uid": "Prometheus"
          },
          "editorMode": "code",
          "expr": "libvirt_domain_memory_stats_used_percent{instance_name=~\"$domain\"}",
          "interval": "",
          "legendFormat": "{{instance_name}}----({{project_name}})",
          "range": true,
          "refId": "A"
        }
      ],
      "thresholds": [],
      "timeRegions": [],
      "title": "Used percent",
      "tooltip": {
        "shared": true,
        "sort": 0,
        "value_type": "individual"
      },
      "type": "graph",
      "xaxis": {
        "mode": "time",
        "show": true,
        "values": []
      },
      "yaxes": [
        {
          "$$hashKey": "object:252",
          "format": "percent",
          "logBase": 1,
          "show": true
        },
        {
          "$$hashKey": "object:253",
          "format": "short",
          "logBase": 1,
          "show": true
        }
      ],
      "yaxis": {
        "align": false
      }
    },
    {
      "aliasColors": {},
      "bars": false,
      "dashLength": 10,
      "dashes": false,
      "datasource": {
        "type": "prometheus",
        "uid": "Prometheus"
      },
      "description": "The total amount of usable memory as seen by the domain. This value may be less than the amount of memory assigned to the domain if a balloon driver is in use or if the guest OS does not initialize all assigned pages. This value is expressed in kB.",
      "fieldConfig": {
        "defaults": {
          "unit": "decbytes"
        },
        "overrides": []
      },
      "fill": 0,
      "fillGradient": 0,
      "gridPos": {
        "h": 8,
        "w": 12,
        "x": 12,
        "y": 18
      },
      "hiddenSeries": false,
      "id": 87,
      "legend": {
        "avg": false,
        "current": false,
        "max": false,
        "min": false,
        "show": true,
        "total": false,
        "values": false
      },
      "lines": true,
      "linewidth": 1,
      "nullPointMode": "null",
      "options": {
        "alertThreshold": true
      },
      "percentage": false,
      "pluginVersion": "9.0.6",
      "pointradius": 2,
      "points": false,
      "renderer": "flot",
      "seriesOverrides": [],
      "spaceLength": 10,
      "stack": false,
      "steppedLine": false,
      "targets": [
        {
          "datasource": {
            "type": "prometheus",
            "uid": "Prometheus"
          },
          "editorMode": "code",
          "expr": "libvirt_domain_memory_stats_available_bytes{instance_name=~\"$domain\"}",
          "interval": "",
          "legendFormat": "{{instance_name}}--({{instance}})",
          "range": true,
          "refId": "A"
        }
      ],
      "thresholds": [],
      "timeRegions": [],
      "title": "Total memory inside vm",
      "tooltip": {
        "shared": true,
        "sort": 0,
        "value_type": "individual"
      },
      "type": "graph",
      "xaxis": {
        "mode": "time",
        "show": true,
        "values": []
      },
      "yaxes": [
        {
          "$$hashKey": "object:172",
          "format": "decbytes",
          "logBase": 1,
          "show": true
        },
        {
          "$$hashKey": "object:173",
          "format": "short",
          "logBase": 1,
          "show": true
        }
      ],
      "yaxis": {
        "align": false
      }
    },
    {
      "aliasColors": {},
      "bars": false,
      "dashLength": 10,
      "dashes": false,
      "datasource": {
        "type": "prometheus",
        "uid": "Prometheus"
      },
      "description": "How much the balloon can be inflated without pushing the guest system to swap, corresponds to 'Available' in /proc/meminfo",
      "fieldConfig": {
        "defaults": {
          "unit": "decbytes"
        },
        "overrides": []
      },
      "fill": 0,
      "fillGradient": 0,
      "gridPos": {
        "h": 8,
        "w": 12,
        "x": 0,
        "y": 26
      },
      "hiddenSeries": false,
      "id": 80,
      "legend": {
        "avg": false,
        "current": false,
        "max": false,
        "min": false,
        "show": true,
        "total": false,
        "values": false
      },
      "lines": true,
      "linewidth": 1,
      "nullPointMode": "null",
      "options": {
        "alertThreshold": true
      },
      "percentage": false,
      "pluginVersion": "9.0.6",
      "pointradius": 2,
      "points": false,
      "renderer": "flot",
      "seriesOverrides": [],
      "spaceLength": 10,
      "stack": false,
      "steppedLine": false,
      "targets": [
        {
          "datasource": {
            "type": "prometheus",
            "uid": "Prometheus"
          },
          "editorMode": "code",
          "expr": "libvirt_domain_memory_stats_usable_bytes{instance_name=~\"$domain\"}",
          "interval": "",
          "legendFormat": "{{instance_name}}---({{instance}})",
          "range": true,
          "refId": "A"
        }
      ],
      "thresholds": [],
      "timeRegions": [],
      "title": "Available memory inside vm",
      "tooltip": {
        "shared": true,
        "sort": 2,
        "value_type": "individual"
      },
      "type": "graph",
      "xaxis": {
        "mode": "time",
        "show": true,
        "values": []
      },
      "yaxes": [
        {
          "format": "decbytes",
          "logBase": 1,
          "show": true
        },
        {
          "format": "none",
          "logBase": 1,
          "show": true
        }
      ],
      "yaxis": {
        "align": false
      }
    },
    {
      "aliasColors": {},
      "bars": false,
      "dashLength": 10,
      "dashes": false,
      "datasource": {
        "type": "prometheus",
        "uid": "Prometheus"
      },
      "description": "The amount of memory left completely unused by the system. Memory that is available but used for reclaimable caches should NOT be reported as free. This value is expressed in kB.",
      "fieldConfig": {
        "defaults": {
          "unit": "bytes"
        },
        "overrides": []
      },
      "fill": 1,
      "fillGradient": 0,
      "gridPos": {
        "h": 8,
        "w": 12,
        "x": 12,
        "y": 26
      },
      "hiddenSeries": false,
      "id": 86,
      "legend": {
        "avg": false,
        "current": false,
        "max": false,
        "min": false,
        "show": true,
        "total": false,
        "values": false
      },
      "lines": true,
      "linewidth": 1,
      "nullPointMode": "null",
      "options": {
        "alertThreshold": true
      },
      "percentage": false,
      "pluginVersion": "9.0.6",
      "pointradius": 2,
      "points": false,
      "renderer": "flot",
      "seriesOverrides": [],
      "spaceLength": 10,
      "stack": false,
      "steppedLine": false,
      "targets": [
        {
          "datasource": {
            "type": "prometheus",
            "uid": "Prometheus"
          },
          "editorMode": "code",
          "expr": "libvirt_domain_memory_stats_unused_bytes{instance_name=~\"$domain\"}",
          "interval": "",
          "legendFormat": "{{instance_name}}",
          "range": true,
          "refId": "A"
        }
      ],
      "thresholds": [],
      "timeRegions": [],
      "title": "Completely unused memory",
      "tooltip": {
        "shared": true,
        "sort": 0,
        "value_type": "individual"
      },
      "type": "graph",
      "xaxis": {
        "mode": "time",
        "show": true,
        "values": []
      },
      "yaxes": [
        {
          "$$hashKey": "object:643",
          "format": "bytes",
          "logBase": 1,
          "show": true
        },
        {
          "$$hashKey": "object:644",
          "format": "short",
          "logBase": 1,
          "show": true
        }
      ],
      "yaxis": {
        "align": false
      }
    },
    {
      "aliasColors": {},
      "bars": false,
      "dashLength": 10,
      "dashes": false,
      "datasource": {
        "type": "prometheus",
        "uid": "Prometheus"
      },
      "description": "Current balloon value (in KB).",
      "fieldConfig": {
        "defaults": {
          "unit": "decbytes"
        },
        "overrides": []
      },
      "fill": 1,
      "fillGradient": 0,
      "gridPos": {
        "h": 8,
        "w": 12,
        "x": 0,
        "y": 34
      },
      "hiddenSeries": false,
      "id": 85,
      "legend": {
        "avg": false,
        "current": false,
        "max": false,
        "min": false,
        "show": true,
        "total": false,
        "values": false
      },
      "lines": true,
      "linewidth": 1,
      "nullPointMode": "null",
      "options": {
        "alertThreshold": true
      },
      "percentage": false,
      "pluginVersion": "9.0.6",
      "pointradius": 2,
      "points": false,
      "renderer": "flot",
      "seriesOverrides": [],
      "spaceLength": 10,
      "stack": false,
      "steppedLine": false,
      "targets": [
        {
          "datasource": {
            "type": "prometheus",
            "uid": "Prometheus"
          },
          "editorMode": "code",
          "expr": "libvirt_domain_memory_stats_actual_balloon_bytes{instance_name=~\"$domain\"}",
          "interval": "",
          "legendFormat": "{{instance_name}}----({{instance}})",
          "range": true,
          "refId": "A"
        }
      ],
      "thresholds": [],
      "timeRegions": [],
      "title": "Current balloon value",
      "tooltip": {
        "shared": true,
        "sort": 0,
        "value_type": "individual"
      },
      "type": "graph",
      "xaxis": {
        "mode": "time",
        "show": true,
        "values": []
      },
      "yaxes": [
        {
          "$$hashKey": "object:491",
          "format": "decbytes",
          "logBase": 1,
          "show": true
        },
        {
          "$$hashKey": "object:492",
          "format": "short",
          "logBase": 1,
          "show": true
        }
      ],
      "yaxis": {
        "align": false
      }
    },
    {
      "aliasColors": {},
      "bars": false,
      "dashLength": 10,
      "dashes": false,
      "datasource": {
        "type": "prometheus",
        "uid": "Prometheus"
      },
      "description": "The amount of memory, that can be quickly reclaimed without additional I/O (in kB).Typically these pages are used for caching files from disk.",
      "fill": 1,
      "fillGradient": 0,
      "gridPos": {
        "h": 8,
        "w": 12,
        "x": 12,
        "y": 34
      },
      "hiddenSeries": false,
      "id": 83,
      "legend": {
        "avg": false,
        "current": false,
        "max": false,
        "min": false,
        "show": true,
        "total": false,
        "values": false
      },
      "lines": true,
      "linewidth": 1,
      "nullPointMode": "null",
      "options": {
        "alertThreshold": true
      },
      "percentage": false,
      "pluginVersion": "9.0.6",
      "pointradius": 2,
      "points": false,
      "renderer": "flot",
      "seriesOverrides": [],
      "spaceLength": 10,
      "stack": false,
      "steppedLine": false,
      "targets": [
        {
          "datasource": {
            "type": "prometheus",
            "uid": "Prometheus"
          },
          "editorMode": "code",
          "expr": "libvirt_domain_memory_stats_disk_cache_bytes{instance_name=~\"$domain\"}",
          "interval": "",
          "legendFormat": "{{instance_name}}-----({{instance}})",
          "range": true,
          "refId": "A"
        }
      ],
      "thresholds": [],
      "timeRegions": [],
      "title": "Cache",
      "tooltip": {
        "shared": true,
        "sort": 0,
        "value_type": "individual"
      },
      "type": "graph",
      "xaxis": {
        "mode": "time",
        "show": true,
        "values": []
      },
      "yaxes": [
        {
          "$$hashKey": "object:562",
          "format": "kbytes",
          "logBase": 1,
          "show": true
        },
        {
          "$$hashKey": "object:563",
          "format": "short",
          "logBase": 1,
          "show": true
        }
      ],
      "yaxis": {
        "align": false
      }
    },
    {
      "aliasColors": {},
      "bars": false,
      "dashLength": 10,
      "dashes": false,
      "datasource": {
        "type": "prometheus",
        "uid": "Prometheus"
      },
      "description": "Page faults occur when a process makes a valid access to virtual memory that is not available. When servicing the page fault, if disk IO is required, it is considered a major fault.",
      "fill": 0,
      "fillGradient": 0,
      "gridPos": {
        "h": 8,
        "w": 12,
        "x": 0,
        "y": 42
      },
      "hiddenSeries": false,
      "id": 84,
      "legend": {
        "avg": false,
        "current": false,
        "max": false,
        "min": false,
        "show": true,
        "total": false,
        "values": false
      },
      "lines": true,
      "linewidth": 1,
      "nullPointMode": "null",
      "options": {
        "alertThreshold": true
      },
      "percentage": false,
      "pluginVersion": "9.0.6",
      "pointradius": 2,
      "points": false,
      "renderer": "flot",
      "seriesOverrides": [],
      "spaceLength": 10,
      "stack": false,
      "steppedLine": false,
      "targets": [
        {
          "datasource": {
            "type": "prometheus",
            "uid": "Prometheus"
          },
          "editorMode": "code",
          "expr": "libvirt_domain_memory_stats_major_fault_total{instance_name=~\"$domain\"}",
          "interval": "",
          "legendFormat": "{{instance_name}}--({{instance}})",
          "range": true,
          "refId": "A"
        }
      ],
      "thresholds": [],
      "timeRegions": [],
      "title": "Major fault",
      "tooltip": {
        "shared": true,
        "sort": 0,
        "value_type": "individual"
      },
      "type": "graph",
      "xaxis": {
        "mode": "time",
        "show": true,
        "values": []
      },
      "yaxes": [
        {
          "format": "short",
          "logBase": 1,
          "show": true
        },
        {
          "format": "short",
          "logBase": 1,
          "show": true
        }
      ],
      "yaxis": {
        "align": false
      }
    },
    {
      "aliasColors": {},
      "bars": false,
      "dashLength": 10,
      "dashes": false,
      "datasource": {
        "type": "prometheus",
        "uid": "Prometheus"
      },
      "description": "Page faults occur when a process makes a valid access to virtual memory that is not available. When servicing the page not fault, if disk IO is required, it is considered a minor fault.",
      "fill": 0,
      "fillGradient": 0,
      "gridPos": {
        "h": 8,
        "w": 12,
        "x": 12,
        "y": 42
      },
      "hiddenSeries": false,
      "id": 81,
      "legend": {
        "avg": false,
        "current": false,
        "max": false,
        "min": false,
        "show": true,
        "total": false,
        "values": false
      },
      "lines": true,
      "linewidth": 1,
      "nullPointMode": "null",
      "options": {
        "alertThreshold": true
      },
      "percentage": false,
      "pluginVersion": "9.0.6",
      "pointradius": 2,
      "points": false,
      "renderer": "flot",
      "seriesOverrides": [],
      "spaceLength": 10,
      "stack": false,
      "steppedLine": false,
      "targets": [
        {
          "datasource": {
            "type": "prometheus",
            "uid": "Prometheus"
          },
          "editorMode": "code",
          "expr": "libvirt_domain_memory_stats_minor_fault_total{instance_name=~\"$domain\"}",
          "interval": "",
          "legendFormat": "{{instance_name}}--({{instance}})",
          "range": true,
          "refId": "A"
        }
      ],
      "thresholds": [],
      "timeRegions": [],
      "title": "Minor fault",
      "tooltip": {
        "shared": true,
        "sort": 0,
        "value_type": "individual"
      },
      "type": "graph",
      "xaxis": {
        "mode": "time",
        "show": true,
        "values": []
      },
      "yaxes": [
        {
          "format": "short",
          "logBase": 1,
          "show": true
        },
        {
          "format": "short",
          "logBase": 1,
          "show": true
        }
      ],
      "yaxis": {
        "align": false
      }
    },
    {
      "aliasColors": {},
      "bars": false,
      "dashLength": 10,
      "dashes": false,
      "datasource": {
        "type": "prometheus",
        "uid": "Prometheus"
      },
      "description": "Resident Set Size of the process running the domain. This value is in kB",
      "fieldConfig": {
        "defaults": {
          "unit": "decbytes"
        },
        "overrides": []
      },
      "fill": 1,
      "fillGradient": 0,
      "gridPos": {
        "h": 9,
        "w": 24,
        "x": 0,
        "y": 50
      },
      "hiddenSeries": false,
      "id": 82,
      "legend": {
        "avg": false,
        "current": false,
        "max": false,
        "min": false,
        "show": true,
        "total": false,
        "values": false
      },
      "lines": true,
      "linewidth": 1,
      "nullPointMode": "null",
      "options": {
        "alertThreshold": true
      },
      "percentage": false,
      "pluginVersion": "9.0.6",
      "pointradius": 2,
      "points": false,
      "renderer": "flot",
      "seriesOverrides": [],
      "spaceLength": 10,
      "stack": false,
      "steppedLine": false,
      "targets": [
        {
          "datasource": {
            "type": "prometheus",
            "uid": "Prometheus"
          },
          "editorMode": "code",
          "expr": "libvirt_domain_memory_stats_rss_bytes{instance_name=~\"$domain\"}",
          "interval": "",
          "legendFormat": "{{instance_name}}--({{instance}})",
          "range": true,
          "refId": "A"
        }
      ],
      "thresholds": [],
      "timeRegions": [],
      "title": "RSS",
      "tooltip": {
        "shared": true,
        "sort": 0,
        "value_type": "individual"
      },
      "type": "graph",
      "xaxis": {
        "mode": "time",
        "show": true,
        "values": []
      },
      "yaxes": [
        {
          "format": "decbytes",
          "logBase": 1,
          "show": true
        },
        {
          "format": "short",
          "logBase": 1,
          "show": true
        }
      ],
      "yaxis": {
        "align": false
      }
    },
    {
      "collapsed": false,
      "datasource": {
        "type": "prometheus",
        "uid": "Y4EtCc7Vk"
      },
      "gridPos": {
        "h": 1,
        "w": 24,
        "x": 0,
        "y": 59
      },
      "id": 38,
      "panels": [],
      "targets": [
        {
          "datasource": {
            "type": "prometheus",
            "uid": "Y4EtCc7Vk"
          },
          "refId": "A"
        }
      ],
      "title": "Network Interface Stats",
      "type": "row"
    },
    {
      "aliasColors": {},
      "bars": false,
      "dashLength": 10,
      "dashes": false,
      "datasource": {
        "type": "prometheus",
        "uid": "Prometheus"
      },
      "description": "Number of bytes transmitted on a network interface, in bytes.",
      "fill": 1,
      "fillGradient": 0,
      "gridPos": {
        "h": 8,
        "w": 12,
        "x": 0,
        "y": 60
      },
      "hiddenSeries": false,
      "id": 48,
      "legend": {
        "avg": false,
        "current": false,
        "max": false,
        "min": false,
        "show": true,
        "total": false,
        "values": false
      },
      "lines": true,
      "linewidth": 1,
      "nullPointMode": "null",
      "options": {
        "alertThreshold": true
      },
      "percentage": false,
      "pluginVersion": "9.0.6",
      "pointradius": 2,
      "points": false,
      "renderer": "flot",
      "seriesOverrides": [
        {
          "$$hashKey": "object:1564",
          "alias": "/.*trans.*/",
          "transform": "negative-Y"
        }
      ],
      "spaceLength": 10,
      "stack": false,
      "steppedLine": false,
      "targets": [
        {
          "datasource": {
            "type": "prometheus",
            "uid": "Prometheus"
          },
          "editorMode": "code",
          "expr": "irate(libvirt_domain_interface_stats_transmit_bytes_total{instance=~\"$instance.*\", instance_name=~\"$domain\"}[5m])",
          "interval": "",
          "legendFormat": "{{instance_name}}--({{instance}})- transmit",
          "range": true,
          "refId": "A"
        },
        {
          "datasource": {
            "type": "prometheus",
            "uid": "Prometheus"
          },
          "editorMode": "code",
          "expr": "irate(libvirt_domain_interface_stats_receive_bytes_total{instance=~\"$instance.*\", instance_name=~\"$domain\"}[5m])",
          "interval": "",
          "legendFormat": "{{instance_name}}--({{instance}})- receive",
          "range": true,
          "refId": "B"
        }
      ],
      "thresholds": [],
      "timeRegions": [],
      "title": "Network traffic",
      "tooltip": {
        "shared": true,
        "sort": 0,
        "value_type": "individual"
      },
      "type": "graph",
      "xaxis": {
        "mode": "time",
        "show": true,
        "values": []
      },
      "yaxes": [
        {
          "$$hashKey": "object:1376",
          "format": "binBps",
          "logBase": 1,
          "show": true
        },
        {
          "$$hashKey": "object:1377",
          "format": "short",
          "logBase": 1,
          "show": true
        }
      ],
      "yaxis": {
        "align": false
      }
    },
    {
      "aliasColors": {},
      "bars": false,
      "dashLength": 10,
      "dashes": false,
      "datasource": {
        "type": "prometheus",
        "uid": "Prometheus"
      },
      "description": "Number of packets received on a network interface.",
      "fill": 1,
      "fillGradient": 0,
      "gridPos": {
        "h": 8,
        "w": 12,
        "x": 12,
        "y": 60
      },
      "hiddenSeries": false,
      "id": 46,
      "legend": {
        "avg": false,
        "current": false,
        "max": false,
        "min": false,
        "show": true,
        "total": false,
        "values": false
      },
      "lines": true,
      "linewidth": 1,
      "nullPointMode": "null",
      "options": {
        "alertThreshold": true
      },
      "percentage": false,
      "pluginVersion": "9.0.6",
      "pointradius": 2,
      "points": false,
      "renderer": "flot",
      "seriesOverrides": [
        {
          "$$hashKey": "object:2689",
          "alias": "/.*trans.*/",
          "transform": "negative-Y"
        }
      ],
      "spaceLength": 10,
      "stack": false,
      "steppedLine": false,
      "targets": [
        {
          "datasource": {
            "type": "prometheus",
            "uid": "Prometheus"
          },
          "editorMode": "code",
          "expr": "rate(libvirt_domain_interface_stats_receive_packets_total{instance=~\"$instance.*\", instance_name=~\"$domain.*\"}[5m])",
          "interval": "",
          "legendFormat": "{{instance_name}}--({{instance}})- receive",
          "range": true,
          "refId": "A"
        },
        {
          "datasource": {
            "type": "prometheus",
            "uid": "Prometheus"
          },
          "expr": "rate(libvirt_domain_interface_stats_transmit_packets_total{instance=~\"$instance.*\", instance_name=~\"$domain\"}[5m])",
          "interval": "",
          "legendFormat": "{{domain}} - transfer",
          "refId": "B"
        }
      ],
      "thresholds": [],
      "timeRegions": [],
      "title": "Network Packets",
      "tooltip": {
        "shared": true,
        "sort": 0,
        "value_type": "individual"
      },
      "type": "graph",
      "xaxis": {
        "mode": "time",
        "show": true,
        "values": []
      },
      "yaxes": [
        {
          "$$hashKey": "object:2639",
          "format": "pps",
          "logBase": 1,
          "show": true
        },
        {
          "$$hashKey": "object:2640",
          "format": "short",
          "logBase": 1,
          "show": true
        }
      ],
      "yaxis": {
        "align": false
      }
    },
    {
      "aliasColors": {},
      "bars": false,
      "dashLength": 10,
      "dashes": false,
      "datasource": {
        "type": "prometheus",
        "uid": "Prometheus"
      },
      "description": "Number of packet transmit drops on a network interface.",
      "fill": 1,
      "fillGradient": 0,
      "gridPos": {
        "h": 8,
        "w": 12,
        "x": 0,
        "y": 68
      },
      "hiddenSeries": false,
      "id": 50,
      "legend": {
        "avg": false,
        "current": false,
        "max": false,
        "min": false,
        "show": true,
        "total": false,
        "values": false
      },
      "lines": true,
      "linewidth": 1,
      "nullPointMode": "null",
      "options": {
        "alertThreshold": true
      },
      "percentage": false,
      "pluginVersion": "9.0.6",
      "pointradius": 2,
      "points": false,
      "renderer": "flot",
      "seriesOverrides": [
        {
          "$$hashKey": "object:1732",
          "alias": "/.*trans.*/",
          "transform": "negative-Y"
        }
      ],
      "spaceLength": 10,
      "stack": false,
      "steppedLine": false,
      "targets": [
        {
          "datasource": {
            "type": "prometheus",
            "uid": "Prometheus"
          },
          "editorMode": "code",
          "expr": "rate(libvirt_domain_interface_stats_transmit_drops_total{instance=~\"$instance.*\", instance_name=~\"$domain.*\"}[5m])",
          "interval": "",
          "legendFormat": "{{instance_name}}--({{instance}})- transmit",
          "range": true,
          "refId": "A"
        },
        {
          "datasource": {
            "type": "prometheus",
            "uid": "Prometheus"
          },
          "editorMode": "code",
          "expr": "rate(libvirt_domain_interface_stats_receive_drops_total{instance=~\"$instance.*\", instance_name=~\"$domain\"}[5m])",
          "interval": "",
          "legendFormat": "{{instance_name}}--({{instance}})-receive",
          "range": true,
          "refId": "B"
        }
      ],
      "thresholds": [],
      "timeRegions": [],
      "title": "Network drops",
      "tooltip": {
        "shared": true,
        "sort": 2,
        "value_type": "individual"
      },
      "type": "graph",
      "xaxis": {
        "mode": "time",
        "show": true,
        "values": []
      },
      "yaxes": [
        {
          "$$hashKey": "object:1702",
          "format": "short",
          "logBase": 1,
          "show": true
        },
        {
          "$$hashKey": "object:1703",
          "format": "short",
          "logBase": 1,
          "show": true
        }
      ],
      "yaxis": {
        "align": false
      }
    },
    {
      "aliasColors": {},
      "bars": false,
      "dashLength": 10,
      "dashes": false,
      "datasource": {
        "type": "prometheus",
        "uid": "Prometheus"
      },
      "description": "Number of packet receive errors on a network interface.",
      "fill": 1,
      "fillGradient": 0,
      "gridPos": {
        "h": 8,
        "w": 12,
        "x": 12,
        "y": 68
      },
      "hiddenSeries": false,
      "id": 105,
      "legend": {
        "avg": false,
        "current": false,
        "max": false,
        "min": false,
        "show": true,
        "total": false,
        "values": false
      },
      "lines": true,
      "linewidth": 1,
      "nullPointMode": "null",
      "options": {
        "alertThreshold": true
      },
      "percentage": false,
      "pluginVersion": "9.0.6",
      "pointradius": 2,
      "points": false,
      "renderer": "flot",
      "seriesOverrides": [
        {
          "$$hashKey": "object:2242",
          "alias": "/.*trans.*/",
          "transform": "negative-Y"
        }
      ],
      "spaceLength": 10,
      "stack": false,
      "steppedLine": false,
      "targets": [
        {
          "datasource": {
            "type": "prometheus",
            "uid": "Prometheus"
          },
          "editorMode": "code",
          "expr": "rate(libvirt_domain_interface_stats_receive_errors_total{instance=~\"$instance.*\", instance_name=~\"$domain.*\"}[5m])",
          "interval": "",
          "legendFormat": "{{instance_name}}--({{instance}})-receive",
          "range": true,
          "refId": "A"
        },
        {
          "datasource": {
            "type": "prometheus",
            "uid": "Prometheus"
          },
          "editorMode": "code",
          "expr": "rate(libvirt_domain_interface_stats_transmit_errors_total{instance=~\"$instance.*\", instance_name=~\"$domain\"}[5m])",
          "interval": "",
          "legendFormat": "{{instance_name}}--({{instance}}) - transmit",
          "range": true,
          "refId": "B"
        }
      ],
      "thresholds": [],
      "timeRegions": [],
      "title": "Network Errors",
      "tooltip": {
        "shared": true,
        "sort": 0,
        "value_type": "individual"
      },
      "type": "graph",
      "xaxis": {
        "mode": "time",
        "show": true,
        "values": []
      },
      "yaxes": [
        {
          "$$hashKey": "object:2214",
          "format": "short",
          "logBase": 1,
          "show": true
        },
        {
          "$$hashKey": "object:2215",
          "format": "short",
          "logBase": 1,
          "show": true
        }
      ],
      "yaxis": {
        "align": false
      }
    },
    {
      "collapsed": false,
      "datasource": {
        "type": "prometheus",
        "uid": "Y4EtCc7Vk"
      },
      "gridPos": {
        "h": 1,
        "w": 24,
        "x": 0,
        "y": 76
      },
      "id": 2,
      "panels": [],
      "targets": [
        {
          "datasource": {
            "type": "prometheus",
            "uid": "Y4EtCc7Vk"
          },
          "refId": "A"
        }
      ],
      "title": "Block Stats ",
      "type": "row"
    },
    {
      "aliasColors": {},
      "bars": false,
      "dashLength": 10,
      "dashes": false,
      "datasource": {
        "type": "prometheus",
        "uid": "Prometheus"
      },
      "description": "Number of write requests to a block device.",
      "fill": 1,
      "fillGradient": 0,
      "gridPos": {
        "h": 8,
        "w": 12,
        "x": 0,
        "y": 77
      },
      "hiddenSeries": false,
      "id": 22,
      "legend": {
        "avg": false,
        "current": false,
        "max": false,
        "min": false,
        "show": true,
        "total": false,
        "values": false
      },
      "lines": true,
      "linewidth": 1,
      "nullPointMode": "null",
      "options": {
        "alertThreshold": true
      },
      "percentage": false,
      "pluginVersion": "9.0.6",
      "pointradius": 2,
      "points": false,
      "renderer": "flot",
      "seriesOverrides": [
        {
          "$$hashKey": "object:4063",
          "alias": "/.*write.*/",
          "transform": "negative-Y"
        }
      ],
      "spaceLength": 10,
      "stack": false,
      "steppedLine": false,
      "targets": [
        {
          "datasource": {
            "type": "prometheus",
            "uid": "Prometheus"
          },
          "editorMode": "code",
          "expr": "irate(libvirt_domain_block_stats_write_requests_total{instance=~\"$instance.*\", instance_name=~\"$domain\"}[5m])",
          "interval": "",
          "legendFormat": "{{instance_name}}--({{instance}}) - write",
          "range": true,
          "refId": "A"
        },
        {
          "datasource": {
            "type": "prometheus",
            "uid": "Prometheus"
          },
          "editorMode": "code",
          "expr": "irate(libvirt_domain_block_stats_read_requests_total{instance=~\"$instance.*\", instance_name=~\"$domain\"}[5m])",
          "interval": "",
          "legendFormat": "{{instance_name}}--({{instance}})- read",
          "range": true,
          "refId": "B"
        }
      ],
      "thresholds": [],
      "timeRegions": [],
      "title": "Write and read requests",
      "tooltip": {
        "shared": true,
        "sort": 0,
        "value_type": "individual"
      },
      "type": "graph",
      "xaxis": {
        "mode": "time",
        "show": true,
        "values": []
      },
      "yaxes": [
        {
          "$$hashKey": "object:4035",
          "format": "short",
          "logBase": 1,
          "show": true
        },
        {
          "$$hashKey": "object:4036",
          "format": "short",
          "logBase": 1,
          "show": true
        }
      ],
      "yaxis": {
        "align": false
      }
    },
    {
      "aliasColors": {},
      "bars": false,
      "dashLength": 10,
      "dashes": false,
      "datasource": {
        "type": "prometheus",
        "uid": "Prometheus"
      },
      "description": "Total time (ns) spent on writes on a block device, in ns, that is, 1/1,000,000,000 of a second, or 109 seconds.",
      "fill": 1,
      "fillGradient": 0,
      "gridPos": {
        "h": 8,
        "w": 12,
        "x": 12,
        "y": 77
      },
      "hiddenSeries": false,
      "id": 123,
      "legend": {
        "avg": false,
        "current": false,
        "max": false,
        "min": false,
        "show": true,
        "total": false,
        "values": false
      },
      "lines": true,
      "linewidth": 1,
      "nullPointMode": "null",
      "options": {
        "alertThreshold": true
      },
      "percentage": false,
      "pluginVersion": "9.0.6",
      "pointradius": 2,
      "points": false,
      "renderer": "flot",
      "seriesOverrides": [
        {
          "$$hashKey": "object:4318",
          "alias": "/.*write.*/",
          "transform": "negative-Y"
        }
      ],
      "spaceLength": 10,
      "stack": false,
      "steppedLine": false,
      "targets": [
        {
          "datasource": {
            "type": "prometheus",
            "uid": "Prometheus"
          },
          "editorMode": "code",
          "expr": "irate(libvirt_domain_block_stats_write_time_seconds_total{instance=~\"$instance.*\", instance_name=~\"$domain\"}[5m])",
          "interval": "",
          "legendFormat": "{{instance_name}}--({{instance}})-write",
          "range": true,
          "refId": "A"
        },
        {
          "datasource": {
            "type": "prometheus",
            "uid": "Prometheus"
          },
          "editorMode": "code",
          "expr": "irate(libvirt_domain_block_stats_read_time_seconds_total{instance=~\"$instance.*\", instance_name=~\"$domain\"}[5m])",
          "interval": "",
          "legendFormat": "{{instance_name}}--({{instance}}) - read",
          "range": true,
          "refId": "B"
        }
      ],
      "thresholds": [],
      "timeRegions": [],
      "title": "Write and read time",
      "tooltip": {
        "shared": true,
        "sort": 0,
        "value_type": "individual"
      },
      "type": "graph",
      "xaxis": {
        "mode": "time",
        "show": true,
        "values": []
      },
      "yaxes": [
        {
          "$$hashKey": "object:4290",
          "format": "ns",
          "logBase": 1,
          "show": true
        },
        {
          "$$hashKey": "object:4291",
          "format": "short",
          "logBase": 1,
          "show": true
        }
      ],
      "yaxis": {
        "align": false
      }
    },
    {
      "aliasColors": {},
      "bars": false,
      "dashLength": 10,
      "dashes": false,
      "datasource": {
        "type": "prometheus",
        "uid": "Prometheus"
      },
      "description": "Number of bytes written to a block device, in bytes.",
      "fill": 1,
      "fillGradient": 0,
      "gridPos": {
        "h": 8,
        "w": 12,
        "x": 0,
        "y": 85
      },
      "hiddenSeries": false,
      "id": 20,
      "legend": {
        "avg": false,
        "current": false,
        "max": false,
        "min": false,
        "show": true,
        "total": false,
        "values": false
      },
      "lines": true,
      "linewidth": 1,
      "nullPointMode": "null",
      "options": {
        "alertThreshold": true
      },
      "percentage": false,
      "pluginVersion": "9.0.6",
      "pointradius": 2,
      "points": false,
      "renderer": "flot",
      "seriesOverrides": [
        {
          "$$hashKey": "object:218",
          "alias": "/.*write.*/",
          "transform": "negative-Y"
        }
      ],
      "spaceLength": 10,
      "stack": false,
      "steppedLine": false,
      "targets": [
        {
          "datasource": {
            "type": "prometheus",
            "uid": "Prometheus"
          },
          "editorMode": "code",
          "exemplar": false,
          "expr": "irate(libvirt_domain_block_stats_write_bytes_total{instance=~\"$instance.*\", instance_name=~\"$domain.*\"}[5m])",
          "instant": false,
          "interval": "",
          "legendFormat": "{{instance_name}}--({{instance}})- write",
          "range": true,
          "refId": "A"
        },
        {
          "datasource": {
            "type": "prometheus",
            "uid": "Prometheus"
          },
          "editorMode": "code",
          "expr": "irate(libvirt_domain_block_stats_read_bytes_total{instance=~\"$instance.*\", instance_name=~\"$domain.*\"}[5m])",
          "interval": "",
          "legendFormat": "{{instance_name}}--({{instance}})- read",
          "range": true,
          "refId": "B"
        }
      ],
      "thresholds": [],
      "timeRegions": [],
      "title": "Write and read bytes",
      "tooltip": {
        "shared": true,
        "sort": 0,
        "value_type": "individual"
      },
      "type": "graph",
      "xaxis": {
        "mode": "time",
        "show": true,
        "values": []
      },
      "yaxes": [
        {
          "$$hashKey": "object:190",
          "format": "binBps",
          "logBase": 1,
          "show": true
        },
        {
          "$$hashKey": "object:191",
          "format": "short",
          "logBase": 1,
          "show": true
        }
      ],
      "yaxis": {
        "align": false
      }
    },
    {
      "aliasColors": {},
      "bars": false,
      "dashLength": 10,
      "dashes": false,
      "datasource": {
        "type": "prometheus",
        "uid": "Prometheus"
      },
      "description": "Total flush requests from a block device.",
      "fill": 1,
      "fillGradient": 0,
      "gridPos": {
        "h": 8,
        "w": 12,
        "x": 12,
        "y": 85
      },
      "hiddenSeries": false,
      "id": 8,
      "legend": {
        "avg": false,
        "current": false,
        "max": false,
        "min": false,
        "show": true,
        "total": false,
        "values": false
      },
      "lines": true,
      "linewidth": 1,
      "nullPointMode": "null",
      "options": {
        "alertThreshold": true
      },
      "percentage": false,
      "pluginVersion": "9.0.6",
      "pointradius": 2,
      "points": false,
      "renderer": "flot",
      "seriesOverrides": [],
      "spaceLength": 10,
      "stack": false,
      "steppedLine": false,
      "targets": [
        {
          "datasource": {
            "type": "prometheus",
            "uid": "Prometheus"
          },
          "editorMode": "code",
          "expr": "irate(libvirt_domain_block_stats_flush_requests_total{instance=~\"$instance.*\", instance_name=~\"$domain\"}[5m])",
          "interval": "",
          "legendFormat": "{{instance_name}}--({{instance}})",
          "range": true,
          "refId": "A"
        }
      ],
      "thresholds": [],
      "timeRegions": [],
      "title": "Flush requests",
      "tooltip": {
        "shared": true,
        "sort": 0,
        "value_type": "individual"
      },
      "type": "graph",
      "xaxis": {
        "mode": "time",
        "show": true,
        "values": []
      },
      "yaxes": [
        {
          "$$hashKey": "object:493",
          "format": "short",
          "logBase": 1,
          "show": true
        },
        {
          "$$hashKey": "object:494",
          "format": "short",
          "logBase": 1,
          "show": true
        }
      ],
      "yaxis": {
        "align": false
      }
    },
    {
      "aliasColors": {},
      "bars": false,
      "dashLength": 10,
      "dashes": false,
      "datasource": {
        "type": "prometheus",
        "uid": "Prometheus"
      },
      "description": "Physical size in bytes of the container of the backing image.",
      "fill": 1,
      "fillGradient": 0,
      "gridPos": {
        "h": 8,
        "w": 12,
        "x": 0,
        "y": 93
      },
      "hiddenSeries": false,
      "id": 12,
      "legend": {
        "avg": false,
        "current": false,
        "max": false,
        "min": false,
        "show": true,
        "total": false,
        "values": false
      },
      "lines": true,
      "linewidth": 1,
      "nullPointMode": "null",
      "options": {
        "alertThreshold": true
      },
      "percentage": false,
      "pluginVersion": "9.0.6",
      "pointradius": 2,
      "points": false,
      "renderer": "flot",
      "seriesOverrides": [],
      "spaceLength": 10,
      "stack": false,
      "steppedLine": false,
      "targets": [
        {
          "datasource": {
            "type": "prometheus",
            "uid": "Prometheus"
          },
          "editorMode": "code",
          "expr": "libvirt_domain_block_stats_physicalsize_bytes{instance=~\"$instance.*\", instance_name=~\"$domain\"}",
          "interval": "",
          "legendFormat": "{{instance_name}}--({{instance}})",
          "range": true,
          "refId": "A"
        }
      ],
      "thresholds": [],
      "timeRegions": [],
      "title": "Physical size of image",
      "tooltip": {
        "shared": true,
        "sort": 0,
        "value_type": "individual"
      },
      "type": "graph",
      "xaxis": {
        "mode": "time",
        "show": true,
        "values": []
      },
      "yaxes": [
        {
          "$$hashKey": "object:651",
          "format": "bytes",
          "logBase": 1,
          "show": true
        },
        {
          "$$hashKey": "object:652",
          "format": "bytes",
          "logBase": 1,
          "show": false
        }
      ],
      "yaxis": {
        "align": false
      }
    },
    {
      "aliasColors": {},
      "bars": false,
      "dashLength": 10,
      "dashes": false,
      "datasource": {
        "type": "prometheus",
        "uid": "Prometheus"
      },
      "description": "Total time (ns) spent on cache flushing to a block device, in ns, that is, 1/1,000,000,000 of a second, or 109 seconds.",
      "fill": 1,
      "fillGradient": 0,
      "gridPos": {
        "h": 8,
        "w": 12,
        "x": 12,
        "y": 93
      },
      "hiddenSeries": false,
      "id": 10,
      "legend": {
        "avg": false,
        "current": false,
        "max": false,
        "min": false,
        "show": true,
        "total": false,
        "values": false
      },
      "lines": true,
      "linewidth": 1,
      "nullPointMode": "null",
      "options": {
        "alertThreshold": true
      },
      "percentage": false,
      "pluginVersion": "9.0.6",
      "pointradius": 2,
      "points": false,
      "renderer": "flot",
      "seriesOverrides": [],
      "spaceLength": 10,
      "stack": false,
      "steppedLine": false,
      "targets": [
        {
          "datasource": {
            "type": "prometheus",
            "uid": "Prometheus"
          },
          "editorMode": "code",
          "expr": "irate(libvirt_domain_block_stats_flush_time_seconds_total{instance=~\"$instance.*\", instance_name=~\"$domain\"}[5m])",
          "interval": "",
          "legendFormat": "{{instance_name}}--({{instance}})",
          "range": true,
          "refId": "A"
        }
      ],
      "thresholds": [],
      "timeRegions": [],
      "title": "Flush time",
      "tooltip": {
        "shared": true,
        "sort": 0,
        "value_type": "individual"
      },
      "type": "graph",
      "xaxis": {
        "mode": "time",
        "show": true,
        "values": []
      },
      "yaxes": [
        {
          "$$hashKey": "object:574",
          "format": "ns",
          "logBase": 1,
          "show": true
        },
        {
          "$$hashKey": "object:575",
          "format": "ns",
          "logBase": 1,
          "show": false
        }
      ],
      "yaxis": {
        "align": false
      }
    },
    {
      "aliasColors": {},
      "bars": false,
      "dashLength": 10,
      "dashes": false,
      "datasource": {
        "type": "prometheus",
        "uid": "Prometheus"
      },
      "description": "Offset of the highest written sector on a block device.",
      "fill": 1,
      "fillGradient": 0,
      "gridPos": {
        "h": 8,
        "w": 12,
        "x": 0,
        "y": 101
      },
      "hiddenSeries": false,
      "id": 4,
      "legend": {
        "avg": false,
        "current": false,
        "max": false,
        "min": false,
        "show": true,
        "total": false,
        "values": false
      },
      "lines": true,
      "linewidth": 1,
      "nullPointMode": "null",
      "options": {
        "alertThreshold": true
      },
      "percentage": false,
      "pluginVersion": "9.0.6",
      "pointradius": 2,
      "points": false,
      "renderer": "flot",
      "seriesOverrides": [],
      "spaceLength": 10,
      "stack": false,
      "steppedLine": false,
      "targets": [
        {
          "datasource": {
            "type": "prometheus",
            "uid": "Prometheus"
          },
          "editorMode": "code",
          "expr": "libvirt_domain_block_stats_allocation{instance=~\"$instance.*\", instance_name=~\"$domain\"}",
          "interval": "",
          "legendFormat": "{{instance_name}}--({{instance}})",
          "range": true,
          "refId": "A"
        }
      ],
      "thresholds": [],
      "timeRegions": [],
      "title": "Image allocation",
      "tooltip": {
        "shared": true,
        "sort": 0,
        "value_type": "individual"
      },
      "type": "graph",
      "xaxis": {
        "mode": "time",
        "show": true,
        "values": []
      },
      "yaxes": [
        {
          "$$hashKey": "object:811",
          "format": "bytes",
          "logBase": 1,
          "show": true
        },
        {
          "$$hashKey": "object:812",
          "format": "short",
          "logBase": 1,
          "show": true
        }
      ],
      "yaxis": {
        "align": false
      }
    },
    {
      "aliasColors": {},
      "bars": false,
      "dashLength": 10,
      "dashes": false,
      "datasource": {
        "type": "prometheus",
        "uid": "Prometheus"
      },
      "description": "Logical size in bytes of the block device\tbacking image.",
      "fill": 1,
      "fillGradient": 0,
      "gridPos": {
        "h": 8,
        "w": 12,
        "x": 12,
        "y": 101
      },
      "hiddenSeries": false,
      "id": 6,
      "legend": {
        "avg": false,
        "current": false,
        "max": false,
        "min": false,
        "show": true,
        "total": false,
        "values": false
      },
      "lines": true,
      "linewidth": 1,
      "nullPointMode": "null",
      "options": {
        "alertThreshold": true
      },
      "percentage": false,
      "pluginVersion": "9.0.6",
      "pointradius": 2,
      "points": false,
      "renderer": "flot",
      "seriesOverrides": [],
      "spaceLength": 10,
      "stack": false,
      "steppedLine": false,
      "targets": [
        {
          "datasource": {
            "type": "prometheus",
            "uid": "Prometheus"
          },
          "editorMode": "code",
          "expr": "libvirt_domain_block_stats_capacity_bytes{instance=~\"$instance.*\", instance_name=~\"$domain\"}",
          "interval": "",
          "legendFormat": "{{instance_name}}--({{instance}})",
          "range": true,
          "refId": "A"
        }
      ],
      "thresholds": [],
      "timeRegions": [],
      "title": "Logical size of the block device\t",
      "tooltip": {
        "shared": true,
        "sort": 0,
        "value_type": "individual"
      },
      "type": "graph",
      "xaxis": {
        "mode": "time",
        "show": true,
        "values": []
      },
      "yaxes": [
        {
          "$$hashKey": "object:892",
          "format": "bytes",
          "logBase": 1,
          "show": true
        },
        {
          "$$hashKey": "object:893",
          "format": "short",
          "logBase": 1,
          "show": true
        }
      ],
      "yaxis": {
        "align": false
      }
    }
  ],
  "refresh": "5s",
  "schemaVersion": 36,
  "style": "dark",
  "tags": [],
  "templating": {
    "list": [
      {
        "current": {},
        "datasource": {
          "type": "prometheus",
          "uid": "Prometheus"
        },
        "definition": "label_values(libvirt_up, instance)",
        "hide": 0,
        "includeAll": true,
        "multi": false,
        "name": "instance",
        "options": [],
        "query": {
          "query": "label_values(libvirt_up, instance)",
          "refId": "StandardVariableQuery"
        },
        "refresh": 1,
        "regex": "/(.*):[0-9]+/",
        "skipUrlSync": false,
        "sort": 1,
        "tagValuesQuery": "",
        "tagsQuery": "",
        "type": "query",
        "useTags": false
      },
      {
        "current": {},
        "datasource": {
          "type": "prometheus",
          "uid": "Prometheus"
        },
        "definition": "label_values(libvirt_domain_info_vstate{instance=~\"$instance.*\"}, instance_name)",
        "hide": 0,
        "includeAll": true,
        "multi": false,
        "name": "domain",
        "options": [],
        "query": {
          "query": "label_values(libvirt_domain_info_vstate{instance=~\"$instance.*\"}, instance_name)",
          "refId": "StandardVariableQuery"
        },
        "refresh": 1,
        "regex": "",
        "skipUrlSync": false,
        "sort": 0,
        "tagValuesQuery": "",
        "tagsQuery": "",
        "type": "query",
        "useTags": false
      },
      {
        "current": {},
        "datasource": {
          "type": "prometheus",
          "uid": "Prometheus"
        },
        "definition": "query_result(label_replace(libvirt_domain_memory_stats_available, \"service\", \"$1\", \"domain\", \"([a-zA-Z-]*)[0-9]*\"))",
        "hide": 0,
        "includeAll": false,
        "multi": false,
        "name": "service",
        "options": [],
        "query": {
          "query": "query_result(label_replace(libvirt_domain_memory_stats_available, \"service\", \"$1\", \"domain\", \"([a-zA-Z-]*)[0-9]*\"))",
          "refId": "Prometheus-service-Variable-Query"
        },
        "refresh": 1,
        "regex": "/.*service=\"([a-zA-Z-]*)\".*/",
        "skipUrlSync": false,
        "sort": 0,
        "tagValuesQuery": "",
        "tagsQuery": "",
        "type": "query",
        "useTags": false
      },
      {
        "current": {
          "selected": true,
          "text": "cloud-sp-dev-lab-metrics",
          "value": "cloud-sp-dev-lab-metrics"
        },
        "hide": 0,
        "includeAll": false,
        "label": "Datasource",
        "multi": false,
        "name": "DS",
        "options": [],
        "query": "prometheus",
        "queryValue": "",
        "refresh": 1,
        "regex": "",
        "skipUrlSync": false,
        "type": "datasource"
      },
      {
        "datasource": {
          "type": "prometheus",
          "uid": "${DS}"
        },
        "filters": [
          {
            "condition": "",
            "key": "instance_name",
            "operator": "!=",
            "value": "instance-maaz--4"
          }
        ],
        "hide": 0,
        "name": "Filters",
        "skipUrlSync": false,
        "type": "adhoc"
      },
      {
        "current": {},
        "datasource": {
          "type": "prometheus",
          "uid": "Prometheus"
        },
        "definition": "label_values(libvirt_domain_info_vstate{instance=~\"$instance.*\"}, domain)",
        "hide": 0,
        "includeAll": false,
        "multi": false,
        "name": "Domain1",
        "options": [],
        "query": {
          "query": "label_values(libvirt_domain_info_vstate{instance=~\"$instance.*\"}, domain)",
          "refId": "StandardVariableQuery"
        },
        "refresh": 1,
        "regex": "",
        "skipUrlSync": false,
        "sort": 0,
        "type": "query"
      }
    ]
  },
  "time": {
    "from": "now-1h",
    "to": "now"
  },
  "timepicker": {},
  "timezone": "",
  "title": "Centralised instance Monitoring",
  "uid": "1sr_0CJGz",
  "version": 96,
  "weekStart": ""
}

